{
  "name": "Travis Williams",
  "age": 31,
  "address": {
    "street": "Vorok Mill",
    "city": "Ziwebci",
    "state": "LA",
    "zip": "12556"
  },
  "contact": {
    "phone": "(918) 378-6880",
    "servicePhone": "800694669"
  },
  "birthday": "1966-02-14T20:53:20.208Z",
  "ip": "132.167.240.42",
  "foo": "bar",
  "profile": {
    "about": "Gi huul aracutofe rivugva durav fisad osewu cojne omi os mougi ro cu. Pizo jovmaahi wib saiwe gunted tesubif ahipob hapa do re ve satalvid we amnid racam wonle edikemo zah. Fotu radiir nop jatnew nodutij paronac on po ufawuv be fiz kazzot kornu mufezog passivitu ta. Hubma usabep wuvat peb has ra ti pusujhu sauj wurepwoz copisko kubtajo ocetosvo ugitus loh wi. Cidwug hidto bimpaw gocehaga mik temno vur emza jolwuge kahlez job dignuv len los on ese. Gesip sapumaj ujle jo hujig ajohorsu tat ige gub rodanlu op votukev. Jigvo sepeere upahah gemajig ew tummugoh bem nahvema tinadi cifga hidu han zoma.",
    "bio": "Adgop ohawpe hi tijifni tib ohezuzrel gej petcutho men buv zoize ijuwiv. Hagsem vib dodo lo suvev hopit tuwbo jub ci mu zi talfowge zufruce emjitah vo guger. Gugkijses rebziizu mazezicuh ese nomdogzi je lis hejnarhuc liwokav jepij irsuz ziz dohpase ecotolih pe hah apaopobuk vi. Wa rovrigu mo rutummes huvopiti mawjus fen genji pomjeva mizuf fapho arguj pukzaje."
  },
  "apiKey": "5c85697033b37f5e72b53bbcdce503d63b64cc6d0124b306ee19a42bfc8ce84d",
  "currency": {
    "code": "ALL",
    "name": "Albania Lek"
  }
}