{
  "name": "Mina Tate",
  "age": 36,
  "address": {
    "street": "Fosu Mill",
    "city": "Cadzadpi",
    "state": "OK",
    "zip": "22468"
  },
  "contact": {
    "phone": "(928) 994-1085",
    "servicePhone": "800483662"
  },
  "birthday": "1960-10-14T05:25:47.809Z",
  "ip": "116.232.42.206",
  "foo": "bar",
  "profile": {
    "about": "Ezegazziz ni kinfacu kaodaime rut nisdagah eb nugwaz ocazimum me wen wafsasnud awoobu kufhut. Ri ke pe emufaj rakubo jobra awta oreos nuw jascib jetri ofojorla lobe. Faguzeril ce debnunesu sike ni nuk gi moapena kesiwkut mefjenuh jusovij newi donza nenlazak fog oteep zomal lakuiv. Mup fevotfez netjic noprupo niv jappoov zaure wa samitef asah lide jazahut luncove ica ze betina zeiphaf.",
    "bio": "Tizzoovo tahunnos pi muhe co vaw musi pehlim na bazkano imopaine gitsaic hec vusocosov. Nipev feniune hade ripriv cum bulebre we zetbe nohjo eva hu purmazec kogtumip. Nob vaj seduwsih hevepo liwek haltidak pinug vo daci bivhu be uva. Ujabe rino jef girfat rud viro junuw uftivit ep pinejil uce istunut cel. Pazaha ji lag hudif re sobom muira uf uhohagdi debbem aha cerejij. Bazini si kazekdu vafouh odu le omelensuj vi ige nu ow pohsedlan er hitnug bar gi ve. Cinabgu nawga juh amju tekanfuh benud dinom op mir kisna ipwezmok pil ub."
  },
  "apiKey": "36dfa39fd8b136df77a3a4a60317ebdecff9c9754ad01fc30db2b767686d56b9",
  "currency": {
    "code": "HNL",
    "name": "Honduras Lempira"
  }
}