{
  "name": "Rhoda Stokes",
  "age": 25,
  "address": {
    "street": "Helec Avenue",
    "city": "Pucelelo",
    "state": "CO",
    "zip": "69508"
  },
  "contact": {
    "phone": "(763) 698-9009",
    "servicePhone": "800352153"
  },
  "birthday": "1988-10-23T23:32:48.214Z",
  "ip": "62.99.187.161",
  "foo": "bar",
  "profile": {
    "about": "Medo eze nimciizi nib omekinef cutbulkej uba kohsuv womofabiv bir lavewihuk uh homed lolowouca. Febmoc anofapek jojtob arnucto cus anu vajut fusemki len faf po mokzerel hasroz kag bo. Bevke zezwol mus ac abob betebba kibase watak de guwij ja irmogez voada kakiz so cicofpot. Irdip nis cavbes se lek nal lot ilawekej kaj lig afjip tig. Useacafi gek is zedapfa vip weju kad wifuheb deonru buzdo rilku ta id pufadij jole coawa orcukdip red. Vuhoif osazidjo pojoscel fevepgi kufepzu ga ro cuf giwahufuh gepole wuwagac ceasepi keminhi ruhfo onfeb oki sem zih. Fe ustebu lobukpu zisvabci lodo pirec uj mowzupsa wekijze naz ve mediti abweva mahenju zewol iraavde fumpad.",
    "bio": "Hanaz arpi paob za hikuce sepukdep faw tarokowo nage of jarra uzuvo efo. Gi miteriw menam jiwos midbusri ti gikasu kojudti or bi rociznug ehas. Viuvkej monopeb sic ejeh me at hul senewkog arecpif fofo aperu wabzog vadocje belubal."
  },
  "apiKey": "7f93929900cfc21073f89ad2b924f11a96404d3f82ea7c736d7334b8dab34a37",
  "currency": {
    "code": "SRD",
    "name": "Suriname Dollar"
  }
}